{
  "scriptId": "382",
  "url": "file:///C:/Users/Administrator/WorkBuddy/Claw/src-tmp/node_modules/.deno/rolldown@1.0.0-rc.17/node_modules/rolldown/dist/shared/define-config-DJOr6Iwt.mjs",
  "functions": [
    {
      "functionName": "",
      "ranges": [
        {
          "startOffset": 0,
          "endOffset": 130,
          "count": 1
        }
      ],
      "isBlockCoverage": true
    },
    {
      "functionName": "defineConfig",
      "ranges": [
        {
          "startOffset": 37,
          "endOffset": 86,
          "count": 0
        }
      ],
      "isBlockCoverage": false
    }
  ]
}