{
  "scriptId": "312",
  "url": "file:///C:/Users/Administrator/WorkBuddy/Claw/src-tmp/packages/adapter-vite/__tests__/build-manifest.test.ts",
  "functions": [
    {
      "functionName": "",
      "ranges": [
        {
          "startOffset": 0,
          "endOffset": 11520,
          "count": 1
        }
      ],
      "isBlockCoverage": true
    },
    {
      "functionName": "makeTempDir",
      "ranges": [
        {
          "startOffset": 420,
          "endOffset": 509,
          "count": 16
        }
      ],
      "isBlockCoverage": true
    },
    {
      "functionName": "cleanup",
      "ranges": [
        {
          "startOffset": 510,
          "endOffset": 605,
          "count": 16
        },
        {
          "startOffset": 594,
          "endOffset": 603,
          "count": 0
        }
      ],
      "isBlockCoverage": true
    },
    {
      "functionName": "",
      "ranges": [
        {
          "startOffset": 725,
          "endOffset": 906,
          "count": 1
        }
      ],
      "isBlockCoverage": true
    },
    {
      "functionName": "",
      "ranges": [
        {
          "startOffset": 958,
          "endOffset": 1890,
          "count": 1
        }
      ],
      "isBlockCoverage": true
    },
    {
      "functionName": "",
      "ranges": [
        {
          "startOffset": 1587,
          "endOffset": 1629,
          "count": 1
        }
      ],
      "isBlockCoverage": true
    },
    {
      "functionName": "",
      "ranges": [
        {
          "startOffset": 1670,
          "endOffset": 1710,
          "count": 2
        }
      ],
      "isBlockCoverage": true
    },
    {
      "functionName": "",
      "ranges": [
        {
          "startOffset": 1941,
          "endOffset": 2451,
          "count": 1
        }
      ],
      "isBlockCoverage": true
    },
    {
      "functionName": "",
      "ranges": [
        {
          "startOffset": 2564,
          "endOffset": 2653,
          "count": 1
        }
      ],
      "isBlockCoverage": true
    },
    {
      "functionName": "",
      "ranges": [
        {
          "startOffset": 2712,
          "endOffset": 3477,
          "count": 1
        }
      ],
      "isBlockCoverage": true
    },
    {
      "functionName": "",
      "ranges": [
        {
          "startOffset": 3282,
          "endOffset": 3310,
          "count": 3
        }
      ],
      "isBlockCoverage": true
    },
    {
      "functionName": "",
      "ranges": [
        {
          "startOffset": 3343,
          "endOffset": 3371,
          "count": 1
        }
      ],
      "isBlockCoverage": true
    },
    {
      "functionName": "",
      "ranges": [
        {
          "startOffset": 3404,
          "endOffset": 3437,
          "count": 2
        }
      ],
      "isBlockCoverage": true
    },
    {
      "functionName": "",
      "ranges": [
        {
          "startOffset": 3593,
          "endOffset": 4043,
          "count": 1
        }
      ],
      "isBlockCoverage": true
    },
    {
      "functionName": "",
      "ranges": [
        {
          "startOffset": 4103,
          "endOffset": 4819,
          "count": 1
        }
      ],
      "isBlockCoverage": true
    },
    {
      "functionName": "",
      "ranges": [
        {
          "startOffset": 4625,
          "endOffset": 4653,
          "count": 2
        }
      ],
      "isBlockCoverage": true
    },
    {
      "functionName": "",
      "ranges": [
        {
          "startOffset": 4698,
          "endOffset": 4726,
          "count": 1
        }
      ],
      "isBlockCoverage": true
    },
    {
      "functionName": "",
      "ranges": [
        {
          "startOffset": 4875,
          "endOffset": 5173,
          "count": 1
        }
      ],
      "isBlockCoverage": true
    },
    {
      "functionName": "",
      "ranges": [
        {
          "startOffset": 5231,
          "endOffset": 5719,
          "count": 1
        }
      ],
      "isBlockCoverage": true
    },
    {
      "functionName": "",
      "ranges": [
        {
          "startOffset": 5625,
          "endOffset": 5679,
          "count": 1
        }
      ],
      "isBlockCoverage": true
    },
    {
      "functionName": "",
      "ranges": [
        {
          "startOffset": 5779,
          "endOffset": 6319,
          "count": 1
        }
      ],
      "isBlockCoverage": true
    },
    {
      "functionName": "",
      "ranges": [
        {
          "startOffset": 6252,
          "endOffset": 6279,
          "count": 3
        }
      ],
      "isBlockCoverage": true
    },
    {
      "functionName": "",
      "ranges": [
        {
          "startOffset": 6380,
          "endOffset": 6857,
          "count": 1
        }
      ],
      "isBlockCoverage": true
    },
    {
      "functionName": "",
      "ranges": [
        {
          "startOffset": 6764,
          "endOffset": 6817,
          "count": 1
        }
      ],
      "isBlockCoverage": true
    },
    {
      "functionName": "",
      "ranges": [
        {
          "startOffset": 6924,
          "endOffset": 7524,
          "count": 1
        }
      ],
      "isBlockCoverage": true
    },
    {
      "functionName": "",
      "ranges": [
        {
          "startOffset": 7593,
          "endOffset": 7920,
          "count": 1
        }
      ],
      "isBlockCoverage": true
    },
    {
      "functionName": "",
      "ranges": [
        {
          "startOffset": 8055,
          "endOffset": 8749,
          "count": 1
        }
      ],
      "isBlockCoverage": true
    },
    {
      "functionName": "",
      "ranges": [
        {
          "startOffset": 8820,
          "endOffset": 9753,
          "count": 1
        }
      ],
      "isBlockCoverage": true
    },
    {
      "functionName": "",
      "ranges": [
        {
          "startOffset": 9839,
          "endOffset": 10397,
          "count": 1
        },
        {
          "startOffset": 10058,
          "endOffset": 10154,
          "count": 20
        }
      ],
      "isBlockCoverage": true
    },
    {
      "functionName": "",
      "ranges": [
        {
          "startOffset": 10457,
          "endOffset": 11040,
          "count": 1
        }
      ],
      "isBlockCoverage": true
    },
    {
      "functionName": "",
      "ranges": [
        {
          "startOffset": 11104,
          "endOffset": 11517,
          "count": 1
        }
      ],
      "isBlockCoverage": true
    }
  ]
}